Metadata-Version: 2.1
Name: socnavgym
Version: 0.1.1
Summary: An environment for Social Navigation
Home-page: https://github.com/gnns4hri/SocNavGym
Author: Sushant Swamy
Author-email: sushantswamy1212@gmail.com
License: GPL-3
License-File: LICENSE
Requires-Dist: gym (>=0.26.2)
Requires-Dist: opencv-python
Requires-Dist: numpy
Requires-Dist: matplotlib
Requires-Dist: shapely
Requires-Dist: Cython
